chart_pip_det-0.1.0.dist-info/licenses/LICENSE
pipdet/__init__.py
pipdet/dataset.py
pipdet/pip.py
pipdet/pipgen.py
pipdet/utils.py
chart_pip_det-0.1.0.dist-info/METADATA
chart_pip_det-0.1.0.dist-info/WHEEL
chart_pip_det-0.1.0.dist-info/top_level.txt
chart_pip_det-0.1.0.dist-info/RECORD
