Metadata-Version: 2.4
Name: chart-pip-det
Version: 0.1.0
Summary: pipdet: is a Python package for detecting perceptually important points in financial market OHLC charts. It efficiently generates pip-level data, enabling the creation of datasets for machine learning and deep learning projects focused on market analysis and technical patterns.
Home-page: https://github.com/mehranESB/chart-pip-detector.git
Author: Mehran ESMAILYBAJEGANI
Author-email: mehranesmaily907@gmail.com
License: MIT
Keywords: chartDL,finance,trading,machine learning,deep learning,OHLCV,technical analysis
Classifier: Development Status :: 3 - Alpha
Classifier: Intended Audience :: Developers
Classifier: Intended Audience :: Science/Research
Classifier: Topic :: Scientific/Engineering :: Artificial Intelligence
Classifier: Topic :: Software Development :: Libraries :: Python Modules
Classifier: Topic :: Office/Business :: Financial
Classifier: Topic :: Utilities
Classifier: License :: OSI Approved :: MIT License
Classifier: Programming Language :: Python :: 3
Classifier: Programming Language :: Python :: 3.8
Classifier: Programming Language :: Python :: 3.9
Classifier: Programming Language :: Python :: 3.10
Requires-Python: >=3.8
License-File: LICENSE
Requires-Dist: pandas
Requires-Dist: numpy
Requires-Dist: matplotlib
Requires-Dist: chart-data-dl
Dynamic: license-file
